LICENSE
MANIFEST.in
README.md
setup.cfg
setup.py
versioneer.py
transmutagen/__init__.py
transmutagen/_version.py
transmutagen/analysis.py
transmutagen/codegen.py
transmutagen/cram.py
transmutagen/generate_json.py
transmutagen/gensolve.py
transmutagen/origen.py
transmutagen/origen_all.py
transmutagen/partialfrac.py
transmutagen/tape9sparse.py
transmutagen/tape9utils.py
transmutagen/util.py
transmutagen.egg-info/PKG-INFO
transmutagen.egg-info/SOURCES.txt
transmutagen.egg-info/dependency_links.txt
transmutagen.egg-info/not-zip-safe
transmutagen.egg-info/requires.txt
transmutagen.egg-info/top_level.txt
transmutagen/data/gensolve.json
transmutagen/data/CRAM_cache/10_200
transmutagen/data/CRAM_cache/11_200
transmutagen/data/CRAM_cache/12_200
transmutagen/data/CRAM_cache/13_200
transmutagen/data/CRAM_cache/14_200
transmutagen/data/CRAM_cache/15_200
transmutagen/data/CRAM_cache/16_200
transmutagen/data/CRAM_cache/17_200
transmutagen/data/CRAM_cache/18_200
transmutagen/data/CRAM_cache/19_200
transmutagen/data/CRAM_cache/1_200
transmutagen/data/CRAM_cache/20_200
transmutagen/data/CRAM_cache/21_200
transmutagen/data/CRAM_cache/22_200
transmutagen/data/CRAM_cache/23_200
transmutagen/data/CRAM_cache/24_200
transmutagen/data/CRAM_cache/25_200
transmutagen/data/CRAM_cache/26_200
transmutagen/data/CRAM_cache/27_200
transmutagen/data/CRAM_cache/28_200
transmutagen/data/CRAM_cache/29_200
transmutagen/data/CRAM_cache/2_200
transmutagen/data/CRAM_cache/30_200
transmutagen/data/CRAM_cache/3_200
transmutagen/data/CRAM_cache/4_200
transmutagen/data/CRAM_cache/5_200
transmutagen/data/CRAM_cache/6_200
transmutagen/data/CRAM_cache/7_200
transmutagen/data/CRAM_cache/8_200
transmutagen/data/CRAM_cache/9_200