Metadata-Version: 1.1
Name: transmutagen
Version: 1.0.2
Summary: Code geneartion tools for transmutation solvers
Home-page: https://github.com/ergs/transmutagen
Author: ERGS
Author-email: ergsonomic@googlegroups.com
License: BSD 3-clause
Download-URL: https://github.com/ergs/transmutagen/zipball/1.0.2
Platform: UNKNOWN
Classifier: License :: OSI Approved
Classifier: Programming Language :: Python
